{
    "with-suffix": {
        "index.js": 2.69
    },
    "universal-date-input": {
        "desktop.js": 128.07,
        "mobile.js": 128.07,
        "index.js": 128.18
    },
    "underlay": {
        "index.js": 3.25
    },
    "typography": {
        "index.js": 5.73
    },
    "tooltip": {
        "desktop.js": 44.35,
        "mobile.js": 70.82,
        "index.js": 97.73
    },
    "toast": {
        "desktop.js": 58.2,
        "mobile.js": 58.19,
        "index.js": 58.67
    },
    "toast-plate": {
        "desktop.js": 15.05,
        "mobile.js": 15.05,
        "index.js": 15.36
    },
    "time-input": {
        "index.js": 18.39
    },
    "textarea": {
        "index.js": 14.52
    },
    "tag": {
        "desktop.js": 4.58,
        "mobile.js": 4.57,
        "index.js": 6.26
    },
    "tabs": {
        "collapsible.js": 183.54,
        "desktop.js": 33.13,
        "mobile.js": 33.29,
        "shared.js": 28.12,
        "index.js": 34.4
    },
    "table": {
        "index.js": 152.88
    },
    "system-message": {
        "desktop.js": 4.61,
        "mobile.js": 4.61,
        "index.js": 7.41
    },
    "switch": {
        "index.js": 4.11
    },
    "steps": {
        "index.js": 8.93
    },
    "stepped-progress-bar": {
        "index.js": 6.53
    },
    "status": {
        "index.js": 1.43
    },
    "stack": {
        "index.js": 0.33
    },
    "spinner": {
        "index.js": 3.91
    },
    "space": {
        "index.js": 2.36
    },
    "sortable-list": {
        "index.js": 53.34
    },
    "slider": {
        "index.js": 29.1
    },
    "slider-input": {
        "index.js": 47.53
    },
    "skeleton": {
        "index.js": 1.44
    },
    "side-panel": {
        "desktop.js": 62.2,
        "mobile.js": 60.41,
        "shared.js": 40.12,
        "index.js": 63.76
    },
    "shared": {
        "index.js": 4.32
    },
    "select": {
        "desktop.js": 141.87,
        "mobile.js": 176.92,
        "shared.js": 155.54,
        "index.js": 201.75
    },
    "select-with-tags": {
        "index.js": 182.45
    },
    "segmented-control": {
        "index.js": 13.22
    },
    "scrollbar": {
        "index.js": 36.67
    },
    "radio": {
        "index.js": 4.14
    },
    "radio-group": {
        "desktop.js": 4.34,
        "mobile.js": 4.33,
        "index.js": 5.88
    },
    "pure-cell": {
        "index.js": 41.89
    },
    "progress-bar": {
        "index.js": 1.61
    },
    "portal": {
        "index.js": 0.56
    },
    "popup-sheet": {
        "index.js": 59.66
    },
    "popover": {
        "index.js": 42.08
    },
    "plate": {
        "desktop.js": 13.84,
        "mobile.js": 13.83,
        "index.js": 14.14
    },
    "picker-button": {
        "desktop.js": 176.47,
        "mobile.js": 189.26,
        "shared.js": 3.01,
        "index.js": 215.49
    },
    "phone-input": {
        "index.js": 28.39
    },
    "pattern-lock": {
        "index.js": 23.64
    },
    "password-input": {
        "index.js": 20.31
    },
    "pass-code": {
        "index.js": 18.77
    },
    "pagination": {
        "index.js": 7.94
    },
    "number-input": {
        "desktop.js": 34.21,
        "mobile.js": 34.2,
        "index.js": 34.9
    },
    "notification": {
        "index.js": 21.65
    },
    "notification-manager": {
        "index.js": 12.87
    },
    "navigation-bar": {
        "shared.js": 16.04,
        "index.js": 19.29
    },
    "mq": {
        "index.js": 2.8
    },
    "modal": {
        "desktop.js": 60.98,
        "mobile.js": 60.98,
        "shared.js": 40.12,
        "index.js": 61.65
    },
    "masked-input": {
        "index.js": 26.81
    },
    "markdown": {
        "desktop.js": 124.75,
        "mobile.js": 124.75,
        "index.js": 126.51
    },
    "loader": {
        "index.js": 1.39
    },
    "list": {
        "index.js": 7.18
    },
    "list-header": {
        "index.js": 5.96
    },
    "link": {
        "index.js": 4.26
    },
    "keyboard-focusable": {
        "index.js": 2.11
    },
    "intl-phone-input": {
        "index.js": 692.34
    },
    "international-phone-input": {
        "desktop.js": 498.47,
        "mobile.js": 503.43,
        "index.js": 529.74
    },
    "input": {
        "desktop.js": 16.98,
        "mobile.js": 16.98,
        "index.js": 17.54
    },
    "input-autocomplete": {
        "desktop.js": 180.23,
        "mobile.js": 188.43,
        "index.js": 214.11
    },
    "indicator": {
        "index.js": 1.99
    },
    "icon-view": {
        "circle.js": 27.51,
        "no-shape.js": 5.1,
        "rectangle.js": 16.16,
        "super-ellipse.js": 53.29
    },
    "icon-button": {
        "index.js": 9.47
    },
    "hatching-progress-bar": {
        "index.js": 1.65
    },
    "grid": {
        "index.js": 2.24
    },
    "global-store": {
        "index.js": 0.33
    },
    "generic-wrapper": {
        "index.js": 1.64
    },
    "gap": {
        "index.js": 1.36
    },
    "gallery": {
        "index.js": 193.52
    },
    "form-control": {
        "desktop.js": 3.82,
        "mobile.js": 3.82,
        "index.js": 6.93
    },
    "filter-tag": {
        "desktop.js": 7.43,
        "mobile.js": 7.43,
        "index.js": 8.99
    },
    "file-upload-item": {
        "index.js": 19.52
    },
    "dropzone": {
        "index.js": 3.5
    },
    "drawer": {
        "index.js": 41.51
    },
    "divider": {
        "index.js": 1.31
    },
    "date-time-input": {
        "desktop.js": 130.71,
        "mobile.js": 224.53,
        "index.js": 225.83
    },
    "date-range-input": {
        "desktop.js": 132.32,
        "mobile.js": 226.18,
        "index.js": 227.49
    },
    "date-input": {
        "index.js": 62.22
    },
    "custom-picker-button": {
        "desktop.js": 177.93,
        "mobile.js": 190.72,
        "index.js": 216.57
    },
    "custom-button": {
        "index.js": 9.3
    },
    "confirmation": {
        "desktop.js": 28.96,
        "mobile.js": 29.07,
        "shared.js": 27.42,
        "index.js": 29.29
    },
    "confirmation-v1": {
        "index.js": 44.22
    },
    "comment": {
        "index.js": 5.9
    },
    "collapse": {
        "index.js": 17.01
    },
    "code-input": {
        "desktop.js": 4.29,
        "mobile.js": 4.29,
        "shared.js": 0,
        "index.js": 7.25
    },
    "circular-progress-bar": {
        "index.js": 8.27
    },
    "checkbox": {
        "index.js": 5.45
    },
    "checkbox-group": {
        "desktop.js": 2.57,
        "mobile.js": 2.57,
        "index.js": 5.44
    },
    "chart": {
        "index.js": 439.29
    },
    "cdn-icon": {
        "index.js": 1.77
    },
    "card-image": {
        "index.js": 2.03
    },
    "calendar": {
        "desktop.js": 63.22,
        "mobile.js": 166.13,
        "shared.js": 46.75,
        "index.js": 166.31
    },
    "calendar-with-skeleton": {
        "index.js": 64.32
    },
    "calendar-range": {
        "index.js": 234.37
    },
    "calendar-input": {
        "desktop.js": 132,
        "mobile.js": 225.84,
        "shared.js": 64.87,
        "index.js": 226.75
    },
    "button": {
        "desktop.js": 7.14,
        "mobile.js": 7.14,
        "index.js": 8.83
    },
    "bottom-sheet": {
        "index.js": 70.13
    },
    "base-modal": {
        "index.js": 40.25
    },
    "bank-card": {
        "index.js": 33.52
    },
    "badge": {
        "index.js": 1.97
    },
    "backdrop": {
        "index.js": 8.85
    },
    "attach": {
        "index.js": 35.39
    },
    "amount": {
        "index.js": 25.87
    },
    "amount-input": {
        "index.js": 45.51
    },
    "alert": {
        "index.js": 14.41
    },
    "action-button": {
        "index.js": 6.48
    }
}