{
  "packageName": "action-button",
  "displayName": "ActionButton",
  "props": {
    "icon": {
      "defaultValue": null,
      "description": "Иконка кнопки",
      "name": "icon",
      "declarations": [
        {
          "fileName": "packages/action-button/src/Component.tsx",
          "name": "TypeLiteral"
        },
        {
          "fileName": "packages/action-button/src/Component.tsx",
          "name": "TypeLiteral"
        }
      ],
      "required": false,
      "type": {
        "name": "ReactNode"
      }
    },
    "size": {
      "defaultValue": {
        "value": 48
      },
      "description": "Размер кнопки",
      "name": "size",
      "declarations": [
        {
          "fileName": "packages/action-button/src/Component.tsx",
          "name": "TypeLiteral"
        },
        {
          "fileName": "packages/action-button/src/Component.tsx",
          "name": "TypeLiteral"
        }
      ],
      "required": false,
      "type": {
        "name": "48 | undefined"
      }
    },
    "view": {
      "defaultValue": {
        "value": "primary"
      },
      "description": "Тип кнопки",
      "name": "view",
      "declarations": [
        {
          "fileName": "packages/action-button/src/Component.tsx",
          "name": "TypeLiteral"
        },
        {
          "fileName": "packages/action-button/src/Component.tsx",
          "name": "TypeLiteral"
        }
      ],
      "required": false,
      "type": {
        "name": "\"primary\" | \"secondary\" | undefined"
      }
    },
    "className": {
      "defaultValue": null,
      "description": "Дополнительный класс",
      "name": "className",
      "declarations": [
        {
          "fileName": "packages/action-button/src/Component.tsx",
          "name": "TypeLiteral"
        },
        {
          "fileName": "core-components/node_modules/@types/react/index.d.ts",
          "name": "HTMLAttributes"
        },
        {
          "fileName": "packages/action-button/src/Component.tsx",
          "name": "TypeLiteral"
        },
        {
          "fileName": "core-components/node_modules/@types/react/index.d.ts",
          "name": "HTMLAttributes"
        }
      ],
      "required": false,
      "type": {
        "name": "string | undefined"
      }
    },
    "iconWrapperClassName": {
      "defaultValue": null,
      "description": "Дополнительный класс для обертки иконки",
      "name": "iconWrapperClassName",
      "declarations": [
        {
          "fileName": "packages/action-button/src/Component.tsx",
          "name": "TypeLiteral"
        },
        {
          "fileName": "packages/action-button/src/Component.tsx",
          "name": "TypeLiteral"
        }
      ],
      "required": false,
      "type": {
        "name": "string | undefined"
      }
    },
    "href": {
      "defaultValue": null,
      "description": "Значение href для ссылки",
      "name": "href",
      "declarations": [
        {
          "fileName": "packages/action-button/src/Component.tsx",
          "name": "TypeLiteral"
        },
        {
          "fileName": "core-components/node_modules/@types/react/index.d.ts",
          "name": "AnchorHTMLAttributes"
        },
        {
          "fileName": "packages/action-button/src/Component.tsx",
          "name": "TypeLiteral"
        }
      ],
      "required": false,
      "type": {
        "name": "string | undefined"
      }
    },
    "disabled": {
      "defaultValue": null,
      "description": "Заблокировать кнопку",
      "name": "disabled",
      "declarations": [
        {
          "fileName": "packages/action-button/src/Component.tsx",
          "name": "TypeLiteral"
        },
        {
          "fileName": "packages/action-button/src/Component.tsx",
          "name": "TypeLiteral"
        },
        {
          "fileName": "core-components/node_modules/@types/react/index.d.ts",
          "name": "ButtonHTMLAttributes"
        }
      ],
      "required": false,
      "type": {
        "name": "boolean | undefined"
      }
    },
    "loading": {
      "defaultValue": null,
      "description": "Показать лоадер",
      "name": "loading",
      "declarations": [
        {
          "fileName": "packages/action-button/src/Component.tsx",
          "name": "TypeLiteral"
        },
        {
          "fileName": "packages/action-button/src/Component.tsx",
          "name": "TypeLiteral"
        }
      ],
      "required": false,
      "type": {
        "name": "boolean | undefined"
      }
    },
    "dataTestId": {
      "defaultValue": null,
      "description": "Идентификатор для систем автоматизированного тестирования.\nДля спиннера используется модификатор -loader",
      "name": "dataTestId",
      "declarations": [
        {
          "fileName": "packages/action-button/src/Component.tsx",
          "name": "TypeLiteral"
        },
        {
          "fileName": "packages/action-button/src/Component.tsx",
          "name": "TypeLiteral"
        }
      ],
      "required": false,
      "type": {
        "name": "string | undefined"
      }
    },
    "colors": {
      "defaultValue": {
        "value": "default"
      },
      "description": "Палитра, в контексте которой используется кнопка",
      "name": "colors",
      "declarations": [
        {
          "fileName": "packages/action-button/src/Component.tsx",
          "name": "TypeLiteral"
        },
        {
          "fileName": "packages/action-button/src/Component.tsx",
          "name": "TypeLiteral"
        }
      ],
      "required": false,
      "type": {
        "name": "Colors | undefined"
      }
    }
  }
}